{
    "key": "group_5cf1605b77a7f",
    "title": "Testimonials",
    "fields": [
        {
            "key": "field_5cf1606583d80",
            "label": "Testimonials background",
            "name": "testimonials_background",
            "type": "image",
            "instructions": "",
            "required": 0,
            "conditional_logic": 0,
            "wrapper": {
                "width": "20",
                "class": "",
                "id": ""
            },
            "return_format": "url",
            "preview_size": "thumbnail",
            "library": "all",
            "min_width": "",
            "min_height": "",
            "min_size": "",
            "max_width": "",
            "max_height": "",
            "max_size": "",
            "mime_types": ""
        },
        {
            "key": "field_5cf161e24638a",
            "label": "Testimonials quote icon",
            "name": "testimonials_quote_icon",
            "type": "image",
            "instructions": "",
            "required": 0,
            "conditional_logic": 0,
            "wrapper": {
                "width": "20",
                "class": "",
                "id": ""
            },
            "return_format": "url",
            "preview_size": "thumbnail",
            "library": "all",
            "min_width": "",
            "min_height": "",
            "min_size": "",
            "max_width": "",
            "max_height": "",
            "max_size": "",
            "mime_types": ""
        },
        {
            "key": "field_5cf160d283d85",
            "label": "Testimonials symbol",
            "name": "testimonials_symbol",
            "type": "text",
            "instructions": "",
            "required": 0,
            "conditional_logic": 0,
            "wrapper": {
                "width": "20",
                "class": "",
                "id": ""
            },
            "default_value": "",
            "placeholder": "",
            "prepend": "",
            "append": "",
            "maxlength": ""
        },
        {
            "key": "field_5cf160e383d86",
            "label": "Testimonials vertical text",
            "name": "testimonials_vertical_text",
            "type": "text",
            "instructions": "",
            "required": 0,
            "conditional_logic": 0,
            "wrapper": {
                "width": "40",
                "class": "",
                "id": ""
            },
            "default_value": "",
            "placeholder": "",
            "prepend": "",
            "append": "",
            "maxlength": ""
        },
        {
            "key": "field_5cf1608483d81",
            "label": "Testimonails",
            "name": "testimonails",
            "type": "repeater",
            "instructions": "",
            "required": 0,
            "conditional_logic": 0,
            "wrapper": {
                "width": "",
                "class": "",
                "id": ""
            },
            "collapsed": "",
            "min": 0,
            "max": 0,
            "layout": "table",
            "button_label": "",
            "sub_fields": [
                {
                    "key": "field_5cf160a483d82",
                    "label": "Author",
                    "name": "author",
                    "type": "text",
                    "instructions": "",
                    "required": 0,
                    "conditional_logic": 0,
                    "wrapper": {
                        "width": "",
                        "class": "",
                        "id": ""
                    },
                    "default_value": "",
                    "placeholder": "",
                    "prepend": "",
                    "append": "",
                    "maxlength": ""
                },
                {
                    "key": "field_5cf160b283d83",
                    "label": "Car",
                    "name": "car",
                    "type": "text",
                    "instructions": "",
                    "required": 0,
                    "conditional_logic": 0,
                    "wrapper": {
                        "width": "",
                        "class": "",
                        "id": ""
                    },
                    "default_value": "",
                    "placeholder": "",
                    "prepend": "",
                    "append": "",
                    "maxlength": ""
                },
                {
                    "key": "field_5cf160b783d84",
                    "label": "Text",
                    "name": "text",
                    "type": "textarea",
                    "instructions": "",
                    "required": 0,
                    "conditional_logic": 0,
                    "wrapper": {
                        "width": "",
                        "class": "",
                        "id": ""
                    },
                    "default_value": "",
                    "placeholder": "",
                    "maxlength": "",
                    "rows": 2,
                    "new_lines": "br"
                }
            ]
        }
    ],
    "location": [
        [
            {
                "param": "post_template",
                "operator": "==",
                "value": "page-templates\/front.php"
            }
        ]
    ],
    "menu_order": 0,
    "position": "normal",
    "style": "default",
    "label_placement": "top",
    "instruction_placement": "label",
    "hide_on_screen": "",
    "active": 1,
    "description": "",
    "modified": 1559323356
}